LICENSE
MANIFEST.in
README.md
README.txt
setup.py
mulpyversus/__init__.py
mulpyversus/asyncleaderboards.py
mulpyversus/asyncmatches.py
mulpyversus/asyncmulpyversus.py
mulpyversus/asyncuser.py
mulpyversus/leaderboards.py
mulpyversus/matches.py
mulpyversus/mulpyversus.py
mulpyversus/user.py
mulpyversus/utils.py
mulpyversus.egg-info/PKG-INFO
mulpyversus.egg-info/SOURCES.txt
mulpyversus.egg-info/dependency_links.txt
mulpyversus.egg-info/top_level.txt