Metadata-Version: 2.1
Name: mulpyversus
Version: 0.1.9
Summary: A Python wrapper for Multiversus API
Home-page: https://github.com/AshladBP/MulpyVersus
Author: Ashlad
Author-email: imadbenbp@gmail.ocm
License: MIT
Keywords: mulpyversus multiversus api python
Platform: UNKNOWN
Classifier: Development Status :: 3 - Alpha 
Classifier: Intended Audience :: Education
Classifier: Operating System :: Microsoft :: Windows :: Windows 10
Classifier: License :: OSI Approved :: MIT License
Classifier: Programming Language :: Python :: 3
License-File: LICENSE
